{
  "env": "Ant-v4",
  "agent": "Optimal_HCGAE_v4",
  "seed": 2,
  "total_steps": 301056,
  "elapsed_s": 174.74501824378967,
  "final_reward": 964.3904667653866,
  "final_std": 13.21615883669046,
  "eval_curve": [
    {
      "steps": 2048,
      "mean_reward": 970.0361471803687,
      "std_reward": 5.9624574062894675
    },
    {
      "steps": 22528,
      "mean_reward": 756.6704245386716,
      "std_reward": 64.62763124594983
    },
    {
      "steps": 43008,
      "mean_reward": 527.647037042852,
      "std_reward": 335.3165224653217
    },
    {
      "steps": 63488,
      "mean_reward": 384.9375032434058,
      "std_reward": 351.47318161513795
    },
    {
      "steps": 83968,
      "mean_reward": 222.0996189782881,
      "std_reward": 248.7091220407776
    },
    {
      "steps": 104448,
      "mean_reward": 397.4060591930008,
      "std_reward": 320.49323348674454
    },
    {
      "steps": 124928,
      "mean_reward": 174.1042621680486,
      "std_reward": 296.989352961355
    },
    {
      "steps": 145408,
      "mean_reward": 541.2153798376004,
      "std_reward": 436.5798769788174
    },
    {
      "steps": 165888,
      "mean_reward": 151.12837531626437,
      "std_reward": 282.90575651823985
    },
    {
      "steps": 186368,
      "mean_reward": 675.6927298097015,
      "std_reward": 349.95204263435915
    },
    {
      "steps": 206848,
      "mean_reward": 893.5396388834204,
      "std_reward": 111.81220013512774
    },
    {
      "steps": 227328,
      "mean_reward": 752.076706263254,
      "std_reward": 41.81082627349589
    },
    {
      "steps": 247808,
      "mean_reward": 919.5086329933911,
      "std_reward": 115.12212492531121
    },
    {
      "steps": 268288,
      "mean_reward": 887.491524188638,
      "std_reward": 48.70881386587275
    },
    {
      "steps": 288768,
      "mean_reward": 940.7945466618672,
      "std_reward": 53.42321858432255
    }
  ],
  "diagnostics": {
    "final_scr_ema": 0.19138876087167353,
    "final_ev_ema": 0.1092200556263151
  }
}