{
  "Hopper-v4": {
    "Optimal_PPO": {
      "steps_mean": 33996.8,
      "steps_std": 3798.47413575504,
      "ev80_mean": 0.9186568282729735,
      "ev150_mean": 0.9813194982705535,
      "aulc_mean": 0.8888921277431014,
      "n": 5
    },
    "Optimal_HCGAE_v2": {
      "steps_mean": 45875.2,
      "steps_std": 9394.048975814423,
      "ev80_mean": 0.9541156731261264,
      "ev150_mean": 0.9725182943899165,
      "aulc_mean": 0.8543196506115287,
      "n": 5
    },
    "Optimal_HCGAE_v2_NoBdry": {
      "steps_mean": 51609.6,
      "steps_std": 10633.834484324081,
      "ev80_mean": 0.9416665972096695,
      "ev150_mean": 0.9768970631421933,
      "aulc_mean": 0.8410761245100765,
      "n": 5
    },
    "Optimal_HCGAE_v2_NoGate": {
      "steps_mean": 50380.8,
      "steps_std": 10248.188725818822,
      "ev80_mean": 0.9314913810687558,
      "ev150_mean": 0.990215760172755,
      "aulc_mean": 0.8547881835930251,
      "n": 5
    },
    "Optimal_HCGAE": {
      "steps_mean": 48332.8,
      "steps_std": 9304.323433759168,
      "ev80_mean": 0.9543935367508428,
      "ev150_mean": 0.990689658142968,
      "aulc_mean": 0.8544470339599888,
      "n": 5
    },
    "speedup_ratio_observed": 0.7410714285714287,
    "speedup_pct_observed": -34.939759036144565,
    "p_steps": 0.05623780387727592,
    "cohens_d_steps": -1.482798978438249
  },
  "Walker2d-v4": {
    "Optimal_PPO": {
      "steps_mean": 40140.8,
      "steps_std": 5277.326838466612,
      "ev80_mean": 0.9658155668755718,
      "ev150_mean": 0.9623808631936341,
      "aulc_mean": 0.9013356578893899,
      "n": 5
    },
    "Optimal_HCGAE_v2": {
      "steps_mean": 52838.4,
      "steps_std": 3523.51242938066,
      "ev80_mean": 0.9677643083857307,
      "ev150_mean": 0.9852397926853309,
      "aulc_mean": 0.8502698468611365,
      "n": 5
    },
    "Optimal_HCGAE_v2_NoBdry": {
      "steps_mean": 56524.8,
      "steps_std": 4411.5270100045855,
      "ev80_mean": 0.9428567361625451,
      "ev150_mean": 0.9762436039000979,
      "aulc_mean": 0.845558675893314,
      "n": 5
    },
    "Optimal_HCGAE_v2_NoGate": {
      "steps_mean": 52838.4,
      "steps_std": 9982.818391616669,
      "ev80_mean": 0.9637534939394415,
      "ev150_mean": 0.9618655087292816,
      "aulc_mean": 0.8407872234693855,
      "n": 5
    },
    "Optimal_HCGAE": {
      "steps_mean": 49971.2,
      "steps_std": 1638.3999999999999,
      "ev80_mean": 0.9539176666844396,
      "ev150_mean": 0.968342405937813,
      "aulc_mean": 0.8440398644884104,
      "n": 5
    },
    "speedup_ratio_observed": 0.7596899224806202,
    "speedup_pct_observed": -31.63265306122449,
    "p_steps": 0.011925233593017595,
    "cohens_d_steps": -2.5311394008759507
  }
}